hns_sunshine_api/__init__.py
hns_sunshine_api/main.py
hns_sunshine_api/sunshine/__init__.py
hns_sunshine_api/sunshine/base.py
hns_sunshine_api/sunshine/events.py
hns_sunshine_api/sunshine/object_records.py
hns_sunshine_api/sunshine/profiles.py
hns_sunshine_api/sunshine/relationship_records.py
hns_sunshine_api-21.7.3.dist-info/LICENSE.txt
hns_sunshine_api-21.7.3.dist-info/METADATA
hns_sunshine_api-21.7.3.dist-info/WHEEL
hns_sunshine_api-21.7.3.dist-info/top_level.txt
hns_sunshine_api-21.7.3.dist-info/RECORD
