Metadata-Version: 2.1
Name: hns-sunshine-api
Version: 21.7.3
Summary: Zendesk sunshine API
Home-page: https://gitlab.com/horsebridge/hns_sunshine_api.git
Author: Nitin Sidhu
Author-email: nitin.sidhu23@gmail.com
License: MIT
Platform: UNKNOWN
Classifier: License :: OSI Approved :: MIT License
Classifier: Operating System :: OS Independent
Classifier: Programming Language :: Python :: 3.6
Classifier: Programming Language :: Python :: 3.7
Classifier: Programming Language :: Python :: 3.8
Requires-Python: ~=3.6
License-File: LICENSE.txt
Requires-Dist: requests (<3,>=2)
